Metadata-Version: 1.0
Name: funniest1022
Version: 0.3
Summary: The funniest joke in the world
Home-page: http://github.com/storborg/funniest1022
Author: Flying Circus
Author-email: flyingcircus@example.com
License: MIT
Platform: UNKNOWN
